[
  {
    "id": "1",
    "title": "如何设计一个好的 TRPG 模组",
    "file": "posts/module-design.md",
    "cover": ["https://images.unsplash.com/photo-1578662996442-48f60103fc96?w=400&h=300&fit=crop"],
    "tags": ["博客", "模组设计", "教程"],
    "createdAt": "2024-03-15T10:00:00Z",
    "updatedAt": "2024-03-15T10:00:00Z"
  },
  {
    "id": "2",
    "title": "跑团记录：永恒恶意",
    "file": "posts/mist-city-record.md",
    "cover": ["/blog/images/img_recruit_coc7_eve_fight.png", "/blog/images/img_recruit_coc7_eve_fight_2.png"],
    "tags": ["杂谈", "跑团记录"],
    "createdAt": "2024-04-01T14:00:00Z",
    "updatedAt": "2024-04-01T14:00:00Z"
  },
  {
    "id": "3",
    "title": "推荐：五个适合新手的模组",
    "file": "posts/beginner-modules.md",
    "tags": ["博客", "推荐", "新手"],
    "createdAt": "2024-04-10T09:00:00Z",
    "updatedAt": "2024-04-10T09:00:00Z"
  },
  {
    "id": "4",
    "title": "CoC 守秘人进阶技巧",
    "file": "posts/coc-keeper-tips.md",
    "cover": ["https://images.unsplash.com/photo-1606567595334-d39972c85dbe?w=400&h=350&fit=crop"],
    "tags": ["博客", "教程", "守秘人"],
    "createdAt": "2024-05-20T08:00:00Z",
    "updatedAt": "2024-05-20T08:00:00Z"
  },
  {
    "id": "5",
    "title": "TRPG 骰子概率速查",
    "file": "posts/dice-probability.md",
    "cover": ["https://images.unsplash.com/photo-1522069169874-c58ec4b76be5?w=400&h=400&fit=crop"],
    "tags": ["博客", "教程", "规则"],
    "createdAt": "2024-06-05T10:00:00Z",
    "updatedAt": "2024-06-05T10:00:00Z"
  },
  {
    "id": "6",
    "title": "Session Zero 完全指南",
    "file": "posts/session-zero-guide.md",
    "tags": ["博客", "教程", "新手"],
    "createdAt": "2024-06-18T09:00:00Z",
    "updatedAt": "2024-06-18T09:00:00Z"
  },
  {
    "id": "7",
    "title": "恐怖氛围音效设计思路",
    "file": "posts/horror-sound-design.md",
    "cover": ["https://images.unsplash.com/photo-1511671782779-c97d3d27a1d4?w=400&h=450&fit=crop"],
    "tags": ["杂谈", "音效", "守秘人"],
    "createdAt": "2024-07-01T14:00:00Z",
    "updatedAt": "2024-07-01T14:00:00Z"
  }
]
